racers_countering/__init__.py
racers_countering/program_code.py
racers_countering-0.0.5.dist-info/METADATA
racers_countering-0.0.5.dist-info/WHEEL
racers_countering-0.0.5.dist-info/licenses/LICENSE
racers_countering-0.0.5.dist-info/RECORD
