Metadata-Version: 2.3
Name: racers_countering
Version: 0.0.5
Summary: A small package that counts TOP-15 racers from data files 
Project-URL: Homepage, https://gitlab.com/mentoring341120/task6
Project-URL: Issues, https://gitlab.com/mentoring341120/task6/issues
Author-email: Volodymyr Nos <nosvolodymyr@gmail.com>
License-File: LICENSE
Classifier: License :: OSI Approved :: MIT License
Classifier: Operating System :: OS Independent
Classifier: Programming Language :: Python :: 3
Requires-Python: >=3.12
